README.txt
setup.py
RE_4/RE_3_file.py
RE_4/__init__.py
RE_4/config.py
RE_4/stats.py
RE_4/zombie_combat.py
RE_4_stuff.egg-info/PKG-INFO
RE_4_stuff.egg-info/SOURCES.txt
RE_4_stuff.egg-info/dependency_links.txt
RE_4_stuff.egg-info/requires.txt
RE_4_stuff.egg-info/top_level.txt