Metadata-Version: 1.1
Name: RE-4-stuff
Version: 0.1
Summary: My Project
Home-page: URL to get it at.
Author: Barbara Rodriguez
Author-email: barbarajrodriguez542@gmail.com
License: UNKNOWN
Download-URL: Where to download it.
Platform: UNKNOWN
